<?xml version="1.0" encoding="utf-8"?>
<abapGit version="v1.0.0" serializer="LCL_OBJECT_XINX" serializer_version="v1.0.0">
 <asx:abap xmlns:asx="http://www.sap.com/abapxml" version="1.0">
  <asx:values>
   <XINX>
    <DD12V>
     <SQLTAB>DRAD</SQLTAB>
     <INDEXNAME>Z01</INDEXNAME>
     <AS4LOCAL>A</AS4LOCAL>
     <DDLANGUAGE>T</DDLANGUAGE>
     <DBINDEX>DRAD~Z01</DBINDEX>
     <DDTEXT>mandt-dokar-dokvr-doktl-dokob-obzae-objky</DDTEXT>
     <ISEXTIND>X</ISEXTIND>
    </DD12V>
    <T_DD17V>
     <DD17V>
      <SQLTAB>DRAD</SQLTAB>
      <INDEXNAME>Z01</INDEXNAME>
      <POSITION>0001</POSITION>
      <AS4LOCAL>A</AS4LOCAL>
      <FIELDNAME>MANDT</FIELDNAME>
     </DD17V>
     <DD17V>
      <SQLTAB>DRAD</SQLTAB>
      <INDEXNAME>Z01</INDEXNAME>
      <POSITION>0002</POSITION>
      <AS4LOCAL>A</AS4LOCAL>
      <FIELDNAME>DOKAR</FIELDNAME>
     </DD17V>
     <DD17V>
      <SQLTAB>DRAD</SQLTAB>
      <INDEXNAME>Z01</INDEXNAME>
      <POSITION>0003</POSITION>
      <AS4LOCAL>A</AS4LOCAL>
      <FIELDNAME>DOKVR</FIELDNAME>
     </DD17V>
     <DD17V>
      <SQLTAB>DRAD</SQLTAB>
      <INDEXNAME>Z01</INDEXNAME>
      <POSITION>0004</POSITION>
      <AS4LOCAL>A</AS4LOCAL>
      <FIELDNAME>DOKTL</FIELDNAME>
     </DD17V>
     <DD17V>
      <SQLTAB>DRAD</SQLTAB>
      <INDEXNAME>Z01</INDEXNAME>
      <POSITION>0005</POSITION>
      <AS4LOCAL>A</AS4LOCAL>
      <FIELDNAME>DOKOB</FIELDNAME>
     </DD17V>
     <DD17V>
      <SQLTAB>DRAD</SQLTAB>
      <INDEXNAME>Z01</INDEXNAME>
      <POSITION>0006</POSITION>
      <AS4LOCAL>A</AS4LOCAL>
      <FIELDNAME>OBZAE</FIELDNAME>
     </DD17V>
     <DD17V>
      <SQLTAB>DRAD</SQLTAB>
      <INDEXNAME>Z01</INDEXNAME>
      <POSITION>0007</POSITION>
      <AS4LOCAL>A</AS4LOCAL>
      <FIELDNAME>OBJKY</FIELDNAME>
     </DD17V>
    </T_DD17V>
   </XINX>
  </asx:values>
 </asx:abap>
</abapGit>
